modbus_api/__init__.py
modbus_api/exception.py
modbus_api/modbus_api.py
modbus_api-1.14.0.dist-info/METADATA
modbus_api-1.14.0.dist-info/WHEEL
modbus_api-1.14.0.dist-info/RECORD
