Metadata-Version: 2.4
Name: modbus-api
Version: 1.14.0
Summary: 
Author: LiuWei
Author-email: 183074632@qq.com
Requires-Python: >=3.11,<4.0
Classifier: Programming Language :: Python :: 3
Classifier: Programming Language :: Python :: 3.11
Classifier: Programming Language :: Python :: 3.12
Classifier: Programming Language :: Python :: 3.13
Classifier: Programming Language :: Python :: 3.14
Requires-Dist: modbus-tk (>=1.1.4,<2.0.0)
